justlucifer123456/__init__.py
justlucifer123456/liudi.py
liudilucifer12345/__init__.py
liudilucifer12345/lsy.py
balabalabala9999999-12.0.9.dist-info/LICENSE
balabalabala9999999-12.0.9.dist-info/METADATA
balabalabala9999999-12.0.9.dist-info/WHEEL
balabalabala9999999-12.0.9.dist-info/top_level.txt
balabalabala9999999-12.0.9.dist-info/RECORD
